[
  {
    "title": "Taming CSS",
    "date": "2015/04/29"
  }, {
    "title": "Hosting on Github",
    "date": "2015/05/16"
  }, {
    "title": "Against CSS in JS",
    "date": "2015/05/29"
  }, {
    "title": "Into the Future of CSS",
    "date": "2015/05/30"
  }, {
    "title": "CSS First",
    "date": "2015/08/01"
  }, {
    "title": "Simply white",
    "date": "2016/01/27"
  }, {
    "title": "Width and absolute positioning",
    "date": "2016/01/30"
  }, {
    "title": "A quest for interchangeable parts",
    "date": "2016/02/06"
  }, {
    "title": "Save scoped CSS",
    "date": "2016/06/09"
  }, {
    "title": "CSS in Depth",
    "date": "2016/08/24"
  }
]
